{
    "DATASOURCE": "0",
    "FILES_DIR": "\/home\/ec2-user\/tmp\/storage-files-thread0-seed:0",
    "NUM_ATTRIBUTES": "2",
    "COLUMN_FORMAT": "INT,INT",
    "DATA_RESOLUTION": "1,1",
    "MIN_VALUES": "10000,10000",
    "MAX_VALUE": "20000,20000",
    "USE_GAMMA": "false",
    "RANGEQUERY_RANGE": "10",
    "VALUE_SIZE": "0",
    "NUM_DATAPOINTS": "16777214",
    "DELETION": "false",
    "SEED": "0",
    "RETRIEVE_EXACTLY": "1,10,20,30,40,50,60",
    "QUERY_RESPONSE_EPSILON": "1",
    "QUERY_INDEX": "87",
    "WHERE_INDEX": "0",
    "QUERY_FUNCTION": "0",
    "POINT_QUERIES": "false",
    "NUM_QUERIES": "100",
    "MAX_SENSITIVITY": "0.001",
    "DATASET": "data\/covid-data.csv",
    "BLOCK_SIZE": "88",
    "NUM_OSMs": "1",
    "ORAM_LOG_CAPACITY": "24",
    "ORAM_Z": "3",
    "STASH_FACTOR": "4",
    "USE_ORAM": "true",
    "BATCH_SIZE": "1",
    "DP_BUCKETS": "0",
    "DP_K": "2",
    "DP_BETA": "20",
    "DP_EPSILON": "0.69299999999999995",
    "FILE_LOGGING": "true",
    "OUT_DIR": ".\/results\/insertionDeletion-size:2^16,23-cols:2-retrieveExactly:1,10,20,30,40,50,60-BlockSize:0",
    "LOG_FILENAME": "0--2024-04-15-09-50-47--6827949110686",
    "InsetionTimes": "162665,24477,25710,24981,24864,25482,24891,24910,24882,25877,25715,24954,25547,25104,25437,24766,24824,25408,25443,25608,25041,24582,24672,24672,24561,24756,24478,24735,25206,25090,25045,25033,25021,25021,24493,24403,24574,24482,24184,24382,24670,24537,24432,24426,24818,24535,24491,24429,24481,24207,24397,24373,24428,24553,24774,24502,24467,25087,24982,25038,25243,25148,25229,24536,24523,24158,24743,24792,24729,24109,23977,24149,24567,24754,24425,24406,24415,24791,24408,24685,24506,26329,25070,25143,25037,24409,24695,25148,24743,24309,24358,24325,24221,24449,24476,24414,24462,24165,24341,24313",
    "DeletionTimes": "98475,97720,98046,97659,97197,96634,96883,96295,96949,96047,97707,97843,106343,95754,96724,96074,96540,95984,95774,94521,96543,94933,95861,96468,95652,94854,95623,96149,95092,94400,94285,94542,94196,94083,95021,94551,94996,94842,95079,94476,95036,94681,94928,95743,95174,95095,94997,95119,94519,94831,95180,95578,94420,94576,94779,94227,94156,94205,94228,94165,95280,94773,95864,94966,95896,93003,93108,93036,92907,94066,92965,93170,93584,93022,94684,95084,94398,95977,95063,94810,94999,94534,94692,94420,93965,94806,95450,93981,94882,95376,94488,94988,94407,95847,94923,95124,94816,94805,94652,94453",
    "aggregates": {
        "insertionTotal": "2612303",
        "insertionMean": "0",
        "timeTotal": "1647427261",
        "timePerQuery": "18935945",
        "realTotal": "1340112859",
        "realPerQuery": "15403596",
        "paddingPerQuery": "3493998",
        "noisePerQuery": "38350",
        "totalPerQuery": "0"
    },
    "QUERIES": [
        {
            "overhead": "13037593",
            "orams": "9557086",
            "beforeOrams": "3463027",
            "afterOrams": "17480",
            "real": "0",
            "padding": "0",
            "noise": "1",
            "total": "1"
        },
        {
            "overhead": "13772567",
            "orams": "10457372",
            "beforeOrams": "3289354",
            "afterOrams": "25841",
            "real": "0",
            "padding": "0",
            "noise": "10",
            "total": "10"
        },
        {
            "overhead": "16807625",
            "orams": "12886611",
            "beforeOrams": "3886683",
            "afterOrams": "34331",
            "real": "0",
            "padding": "0",
            "noise": "20",
            "total": "20"
        },
        {
            "overhead": "18548824",
            "orams": "14663460",
            "beforeOrams": "3851243",
            "afterOrams": "34121",
            "real": "0",
            "padding": "0",
            "noise": "30",
            "total": "30"
        },
        {
            "overhead": "21015075",
            "orams": "17138892",
            "beforeOrams": "3834672",
            "afterOrams": "41511",
            "real": "0",
            "padding": "0",
            "noise": "40",
            "total": "40"
        },
        {
            "overhead": "23742939",
            "orams": "19829115",
            "beforeOrams": "3855213",
            "afterOrams": "58611",
            "real": "0",
            "padding": "0",
            "noise": "50",
            "total": "50"
        },
        {
            "overhead": "25841014",
            "orams": "22491888",
            "beforeOrams": "3294054",
            "afterOrams": "55072",
            "real": "0",
            "padding": "0",
            "noise": "60",
            "total": "60"
        },
        {
            "overhead": "12216370",
            "orams": "8929267",
            "beforeOrams": "3274143",
            "afterOrams": "12960",
            "real": "0",
            "padding": "0",
            "noise": "1",
            "total": "1"
        },
        {
            "overhead": "14106701",
            "orams": "10820418",
            "beforeOrams": "3260193",
            "afterOrams": "26090",
            "real": "0",
            "padding": "0",
            "noise": "10",
            "total": "10"
        },
        {
            "overhead": "16638722",
            "orams": "12969892",
            "beforeOrams": "3641590",
            "afterOrams": "27240",
            "real": "0",
            "padding": "0",
            "noise": "20",
            "total": "20"
        },
        {
            "overhead": "19342827",
            "orams": "16057923",
            "beforeOrams": "3243123",
            "afterOrams": "41781",
            "real": "0",
            "padding": "0",
            "noise": "30",
            "total": "30"
        },
        {
            "overhead": "20470006",
            "orams": "17134072",
            "beforeOrams": "3283733",
            "afterOrams": "52201",
            "real": "0",
            "padding": "0",
            "noise": "40",
            "total": "40"
        },
        {
            "overhead": "23764419",
            "orams": "19886715",
            "beforeOrams": "3829873",
            "afterOrams": "47831",
            "real": "0",
            "padding": "0",
            "noise": "50",
            "total": "50"
        },
        {
            "overhead": "25007109",
            "orams": "21698765",
            "beforeOrams": "3254023",
            "afterOrams": "54321",
            "real": "0",
            "padding": "0",
            "noise": "60",
            "total": "60"
        },
        {
            "overhead": "12930692",
            "orams": "9044289",
            "beforeOrams": "3873663",
            "afterOrams": "12740",
            "real": "0",
            "padding": "0",
            "noise": "1",
            "total": "1"
        },
        {
            "overhead": "14457097",
            "orams": "11155872",
            "beforeOrams": "3275384",
            "afterOrams": "25841",
            "real": "0",
            "padding": "0",
            "noise": "10",
            "total": "10"
        },
        {
            "overhead": "17200872",
            "orams": "13333758",
            "beforeOrams": "3833153",
            "afterOrams": "33961",
            "real": "0",
            "padding": "0",
            "noise": "20",
            "total": "20"
        },
        {
            "overhead": "18628516",
            "orams": "15350913",
            "beforeOrams": "3243703",
            "afterOrams": "33900",
            "real": "0",
            "padding": "0",
            "noise": "30",
            "total": "30"
        },
        {
            "overhead": "24092965",
            "orams": "20774410",
            "beforeOrams": "3257274",
            "afterOrams": "61281",
            "real": "0",
            "padding": "0",
            "noise": "50",
            "total": "50"
        },
        {
            "overhead": "26986682",
            "orams": "23086808",
            "beforeOrams": "3828453",
            "afterOrams": "71421",
            "real": "0",
            "padding": "0",
            "noise": "60",
            "total": "60"
        },
        {
            "overhead": "12380444",
            "orams": "8468989",
            "beforeOrams": "3898304",
            "afterOrams": "13151",
            "real": "0",
            "padding": "0",
            "noise": "1",
            "total": "1"
        },
        {
            "overhead": "15034176",
            "orams": "11147772",
            "beforeOrams": "3864533",
            "afterOrams": "21871",
            "real": "0",
            "padding": "0",
            "noise": "10",
            "total": "10"
        },
        {
            "overhead": "16834116",
            "orams": "13522132",
            "beforeOrams": "3277243",
            "afterOrams": "34741",
            "real": "0",
            "padding": "0",
            "noise": "20",
            "total": "20"
        },
        {
            "overhead": "19288756",
            "orams": "15946821",
            "beforeOrams": "3299354",
            "afterOrams": "42581",
            "real": "0",
            "padding": "0",
            "noise": "30",
            "total": "30"
        },
        {
            "overhead": "21376650",
            "orams": "18051785",
            "beforeOrams": "3282464",
            "afterOrams": "42401",
            "real": "0",
            "padding": "0",
            "noise": "40",
            "total": "40"
        },
        {
            "overhead": "24718715",
            "orams": "21305038",
            "beforeOrams": "3363116",
            "afterOrams": "50561",
            "real": "0",
            "padding": "0",
            "noise": "50",
            "total": "50"
        },
        {
            "overhead": "25617500",
            "orams": "22243044",
            "beforeOrams": "3307145",
            "afterOrams": "67311",
            "real": "0",
            "padding": "0",
            "noise": "60",
            "total": "60"
        },
        {
            "overhead": "12858741",
            "orams": "8992537",
            "beforeOrams": "3850263",
            "afterOrams": "15941",
            "real": "0",
            "padding": "0",
            "noise": "1",
            "total": "1"
        },
        {
            "overhead": "16306999",
            "orams": "13017874",
            "beforeOrams": "3260254",
            "afterOrams": "28871",
            "real": "0",
            "padding": "0",
            "noise": "20",
            "total": "20"
        },
        {
            "overhead": "18934760",
            "orams": "15082436",
            "beforeOrams": "3818903",
            "afterOrams": "33421",
            "real": "0",
            "padding": "0",
            "noise": "30",
            "total": "30"
        },
        {
            "overhead": "21804857",
            "orams": "17883282",
            "beforeOrams": "3869864",
            "afterOrams": "51711",
            "real": "0",
            "padding": "0",
            "noise": "40",
            "total": "40"
        },
        {
            "overhead": "23627937",
            "orams": "20309592",
            "beforeOrams": "3258584",
            "afterOrams": "59761",
            "real": "0",
            "padding": "0",
            "noise": "50",
            "total": "50"
        },
        {
            "overhead": "26037687",
            "orams": "22734482",
            "beforeOrams": "3248714",
            "afterOrams": "54491",
            "real": "0",
            "padding": "0",
            "noise": "60",
            "total": "60"
        },
        {
            "overhead": "12606097",
            "orams": "9334174",
            "beforeOrams": "3255703",
            "afterOrams": "16220",
            "real": "0",
            "padding": "0",
            "noise": "1",
            "total": "1"
        },
        {
            "overhead": "14559868",
            "orams": "11280064",
            "beforeOrams": "3255224",
            "afterOrams": "24580",
            "real": "0",
            "padding": "0",
            "noise": "10",
            "total": "10"
        },
        {
            "overhead": "16458080",
            "orams": "13186017",
            "beforeOrams": "3243193",
            "afterOrams": "28870",
            "real": "0",
            "padding": "0",
            "noise": "20",
            "total": "20"
        },
        {
            "overhead": "19208464",
            "orams": "15258530",
            "beforeOrams": "3915754",
            "afterOrams": "34180",
            "real": "0",
            "padding": "0",
            "noise": "30",
            "total": "30"
        },
        {
            "overhead": "22494939",
            "orams": "18132777",
            "beforeOrams": "4319521",
            "afterOrams": "42641",
            "real": "0",
            "padding": "0",
            "noise": "40",
            "total": "40"
        },
        {
            "overhead": "23623527",
            "orams": "20325754",
            "beforeOrams": "3250093",
            "afterOrams": "47680",
            "real": "0",
            "padding": "0",
            "noise": "50",
            "total": "50"
        },
        {
            "overhead": "25633220",
            "orams": "21723326",
            "beforeOrams": "3854773",
            "afterOrams": "55121",
            "real": "0",
            "padding": "0",
            "noise": "60",
            "total": "60"
        },
        {
            "overhead": "14145251",
            "orams": "10841548",
            "beforeOrams": "3278143",
            "afterOrams": "25560",
            "real": "0",
            "padding": "0",
            "noise": "10",
            "total": "10"
        },
        {
            "overhead": "16620052",
            "orams": "12747979",
            "beforeOrams": "3843823",
            "afterOrams": "28250",
            "real": "0",
            "padding": "0",
            "noise": "20",
            "total": "20"
        },
        {
            "overhead": "19177765",
            "orams": "15905901",
            "beforeOrams": "3236833",
            "afterOrams": "35031",
            "real": "0",
            "padding": "0",
            "noise": "30",
            "total": "30"
        },
        {
            "overhead": "23217101",
            "orams": "19878716",
            "beforeOrams": "3277584",
            "afterOrams": "60801",
            "real": "0",
            "padding": "0",
            "noise": "50",
            "total": "50"
        },
        {
            "overhead": "26001367",
            "orams": "22098322",
            "beforeOrams": "3836743",
            "afterOrams": "66302",
            "real": "0",
            "padding": "0",
            "noise": "60",
            "total": "60"
        },
        {
            "overhead": "12358852",
            "orams": "9085809",
            "beforeOrams": "3256913",
            "afterOrams": "16130",
            "real": "0",
            "padding": "0",
            "noise": "1",
            "total": "1"
        },
        {
            "overhead": "14551709",
            "orams": "10690095",
            "beforeOrams": "3831173",
            "afterOrams": "30441",
            "real": "0",
            "padding": "0",
            "noise": "10",
            "total": "10"
        },
        {
            "overhead": "17078270",
            "orams": "13548903",
            "beforeOrams": "3500537",
            "afterOrams": "28830",
            "real": "0",
            "padding": "0",
            "noise": "20",
            "total": "20"
        },
        {
            "overhead": "18293919",
            "orams": "15000496",
            "beforeOrams": "3250623",
            "afterOrams": "42800",
            "real": "0",
            "padding": "0",
            "noise": "30",
            "total": "30"
        },
        {
            "overhead": "21167378",
            "orams": "17870753",
            "beforeOrams": "3245604",
            "afterOrams": "51021",
            "real": "0",
            "padding": "0",
            "noise": "40",
            "total": "40"
        },
        {
            "overhead": "23457424",
            "orams": "20177990",
            "beforeOrams": "3230933",
            "afterOrams": "48501",
            "real": "0",
            "padding": "0",
            "noise": "50",
            "total": "50"
        },
        {
            "overhead": "12338201",
            "orams": "9085248",
            "beforeOrams": "3238773",
            "afterOrams": "14180",
            "real": "0",
            "padding": "0",
            "noise": "1",
            "total": "1"
        },
        {
            "overhead": "14945545",
            "orams": "11046292",
            "beforeOrams": "3874233",
            "afterOrams": "25020",
            "real": "0",
            "padding": "0",
            "noise": "10",
            "total": "10"
        },
        {
            "overhead": "17268712",
            "orams": "13966728",
            "beforeOrams": "3267993",
            "afterOrams": "33991",
            "real": "0",
            "padding": "0",
            "noise": "20",
            "total": "20"
        },
        {
            "overhead": "19060272",
            "orams": "15780929",
            "beforeOrams": "3236273",
            "afterOrams": "43070",
            "real": "0",
            "padding": "0",
            "noise": "30",
            "total": "30"
        },
        {
            "overhead": "21281679",
            "orams": "18004226",
            "beforeOrams": "3235403",
            "afterOrams": "42050",
            "real": "0",
            "padding": "0",
            "noise": "40",
            "total": "40"
        },
        {
            "overhead": "12688688",
            "orams": "9450925",
            "beforeOrams": "3220623",
            "afterOrams": "17140",
            "real": "0",
            "padding": "0",
            "noise": "1",
            "total": "1"
        },
        {
            "overhead": "14814343",
            "orams": "10926349",
            "beforeOrams": "3864143",
            "afterOrams": "23851",
            "real": "0",
            "padding": "0",
            "noise": "10",
            "total": "10"
        },
        {
            "overhead": "16683622",
            "orams": "13392450",
            "beforeOrams": "3261822",
            "afterOrams": "29350",
            "real": "0",
            "padding": "0",
            "noise": "20",
            "total": "20"
        },
        {
            "overhead": "18382871",
            "orams": "15069396",
            "beforeOrams": "3279004",
            "afterOrams": "34471",
            "real": "0",
            "padding": "0",
            "noise": "30",
            "total": "30"
        },
        {
            "overhead": "22725602",
            "orams": "18753837",
            "beforeOrams": "3917454",
            "afterOrams": "54311",
            "real": "0",
            "padding": "0",
            "noise": "40",
            "total": "40"
        },
        {
            "overhead": "24248557",
            "orams": "20940923",
            "beforeOrams": "3248003",
            "afterOrams": "59631",
            "real": "0",
            "padding": "0",
            "noise": "50",
            "total": "50"
        },
        {
            "overhead": "26916992",
            "orams": "22882355",
            "beforeOrams": "3965915",
            "afterOrams": "68722",
            "real": "0",
            "padding": "0",
            "noise": "60",
            "total": "60"
        },
        {
            "overhead": "12042528",
            "orams": "8753164",
            "beforeOrams": "3273414",
            "afterOrams": "15950",
            "real": "0",
            "padding": "0",
            "noise": "1",
            "total": "1"
        },
        {
            "overhead": "15016357",
            "orams": "10929299",
            "beforeOrams": "4061397",
            "afterOrams": "25661",
            "real": "0",
            "padding": "0",
            "noise": "10",
            "total": "10"
        },
        {
            "overhead": "17151981",
            "orams": "13855568",
            "beforeOrams": "3261802",
            "afterOrams": "34611",
            "real": "0",
            "padding": "0",
            "noise": "20",
            "total": "20"
        },
        {
            "overhead": "18832819",
            "orams": "15529204",
            "beforeOrams": "3261484",
            "afterOrams": "42131",
            "real": "0",
            "padding": "0",
            "noise": "30",
            "total": "30"
        },
        {
            "overhead": "21369591",
            "orams": "18076057",
            "beforeOrams": "3242393",
            "afterOrams": "51141",
            "real": "0",
            "padding": "0",
            "noise": "40",
            "total": "40"
        },
        {
            "overhead": "23272992",
            "orams": "19979368",
            "beforeOrams": "3244663",
            "afterOrams": "48961",
            "real": "0",
            "padding": "0",
            "noise": "50",
            "total": "50"
        },
        {
            "overhead": "26087787",
            "orams": "22151653",
            "beforeOrams": "3866523",
            "afterOrams": "69611",
            "real": "0",
            "padding": "0",
            "noise": "60",
            "total": "60"
        },
        {
            "overhead": "14817922",
            "orams": "11553128",
            "beforeOrams": "3242413",
            "afterOrams": "22381",
            "real": "0",
            "padding": "0",
            "noise": "10",
            "total": "10"
        },
        {
            "overhead": "19449408",
            "orams": "15393862",
            "beforeOrams": "4011475",
            "afterOrams": "44071",
            "real": "0",
            "padding": "0",
            "noise": "30",
            "total": "30"
        },
        {
            "overhead": "21997820",
            "orams": "18109346",
            "beforeOrams": "3836173",
            "afterOrams": "52301",
            "real": "0",
            "padding": "0",
            "noise": "40",
            "total": "40"
        },
        {
            "overhead": "23731960",
            "orams": "20388385",
            "beforeOrams": "3293674",
            "afterOrams": "49901",
            "real": "0",
            "padding": "0",
            "noise": "50",
            "total": "50"
        },
        {
            "overhead": "26031367",
            "orams": "22103373",
            "beforeOrams": "3872864",
            "afterOrams": "55130",
            "real": "0",
            "padding": "0",
            "noise": "60",
            "total": "60"
        },
        {
            "overhead": "12514325",
            "orams": "9244141",
            "beforeOrams": "3253803",
            "afterOrams": "16381",
            "real": "0",
            "padding": "0",
            "noise": "1",
            "total": "1"
        },
        {
            "overhead": "14671261",
            "orams": "10815127",
            "beforeOrams": "3834863",
            "afterOrams": "21271",
            "real": "0",
            "padding": "0",
            "noise": "10",
            "total": "10"
        },
        {
            "overhead": "16477790",
            "orams": "13164336",
            "beforeOrams": "3278854",
            "afterOrams": "34600",
            "real": "0",
            "padding": "0",
            "noise": "20",
            "total": "20"
        },
        {
            "overhead": "18432251",
            "orams": "15144498",
            "beforeOrams": "3252623",
            "afterOrams": "35130",
            "real": "0",
            "padding": "0",
            "noise": "30",
            "total": "30"
        },
        {
            "overhead": "24129205",
            "orams": "20221841",
            "beforeOrams": "3846063",
            "afterOrams": "61301",
            "real": "0",
            "padding": "0",
            "noise": "50",
            "total": "50"
        },
        {
            "overhead": "25669271",
            "orams": "22362997",
            "beforeOrams": "3251013",
            "afterOrams": "55261",
            "real": "0",
            "padding": "0",
            "noise": "60",
            "total": "60"
        },
        {
            "overhead": "12349862",
            "orams": "9070769",
            "beforeOrams": "3266043",
            "afterOrams": "13050",
            "real": "0",
            "padding": "0",
            "noise": "1",
            "total": "1"
        },
        {
            "overhead": "14267115",
            "orams": "11001840",
            "beforeOrams": "3244284",
            "afterOrams": "20991",
            "real": "0",
            "padding": "0",
            "noise": "10",
            "total": "10"
        },
        {
            "overhead": "16916937",
            "orams": "13009322",
            "beforeOrams": "3873794",
            "afterOrams": "33821",
            "real": "0",
            "padding": "0",
            "noise": "20",
            "total": "20"
        },
        {
            "overhead": "18771678",
            "orams": "15480423",
            "beforeOrams": "3248134",
            "afterOrams": "43121",
            "real": "0",
            "padding": "0",
            "noise": "30",
            "total": "30"
        },
        {
            "overhead": "25730582",
            "orams": "22446378",
            "beforeOrams": "3225233",
            "afterOrams": "58971",
            "real": "0",
            "padding": "0",
            "noise": "60",
            "total": "60"
        },
        {
            "overhead": "12256132",
            "orams": "8968658",
            "beforeOrams": "3270804",
            "afterOrams": "16670",
            "real": "0",
            "padding": "0",
            "noise": "1",
            "total": "1"
        }
    ]
}
